long_document_mcp/README.md
long_document_mcp/__init__.py
long_document_mcp/conftest.py
long_document_mcp/doc_tool_server.py
long_document_mcp/test_doc_tool_server.py
long_document_mcp-0.0.3.dist-info/METADATA
long_document_mcp-0.0.3.dist-info/WHEEL
long_document_mcp-0.0.3.dist-info/entry_points.txt
long_document_mcp-0.0.3.dist-info/top_level.txt
long_document_mcp-0.0.3.dist-info/RECORD
