Metadata-Version: 2.4
Name: long-document-mcp
Version: 0.0.3
Summary: A MCP server for managing structured long Markdown documents
Author: clchinkc
License: MIT License
Project-URL: Homepage, https://github.com/long-document-mcp/long-document-mcp
Project-URL: Bug Tracker, https://github.com/long-document-mcp/long-document-mcp/issues
Classifier: Programming Language :: Python :: 3
Classifier: Operating System :: OS Independent
Requires-Python: >=3.8
Requires-Dist: fastapi
Requires-Dist: uvicorn[standard]
Requires-Dist: pydantic-ai
Requires-Dist: mcp[cli]
Requires-Dist: python-dotenv
Requires-Dist: google-generativeai
Provides-Extra: dev
Requires-Dist: pytest; extra == "dev"
Requires-Dist: pytest-asyncio; extra == "dev"
